JavascriptBiaozhunCankaoJiaocheng/README.md
JavascriptBiaozhunCankaoJiaocheng/__init__.py
JavascriptBiaozhunCankaoJiaocheng/__main__.py
JavascriptBiaozhunCankaoJiaocheng/file.epub
JavascriptBiaozhunCankaoJiaocheng/index.html
JavascriptBiaozhunCankaoJiaocheng/css/__init__.py
JavascriptBiaozhunCankaoJiaocheng/css/annotations.css
JavascriptBiaozhunCankaoJiaocheng/css/main.css
JavascriptBiaozhunCankaoJiaocheng/css/normalize.css
JavascriptBiaozhunCankaoJiaocheng/css/popup.css
JavascriptBiaozhunCankaoJiaocheng/font/__init__.py
JavascriptBiaozhunCankaoJiaocheng/font/fontello.eot
JavascriptBiaozhunCankaoJiaocheng/font/fontello.svg
JavascriptBiaozhunCankaoJiaocheng/font/fontello.ttf
JavascriptBiaozhunCankaoJiaocheng/font/fontello.woff
JavascriptBiaozhunCankaoJiaocheng/img/__init__.py
JavascriptBiaozhunCankaoJiaocheng/img/annotator-glyph-sprite.png
JavascriptBiaozhunCankaoJiaocheng/img/annotator-icon-sprite.png
JavascriptBiaozhunCankaoJiaocheng/img/apple-touch-icon.png
JavascriptBiaozhunCankaoJiaocheng/img/cancelfullscreen.png
JavascriptBiaozhunCankaoJiaocheng/img/close.png
JavascriptBiaozhunCankaoJiaocheng/img/fullscreen.png
JavascriptBiaozhunCankaoJiaocheng/img/loader.gif
JavascriptBiaozhunCankaoJiaocheng/img/menu-icon.png
JavascriptBiaozhunCankaoJiaocheng/img/save.png
JavascriptBiaozhunCankaoJiaocheng/img/saved.png
JavascriptBiaozhunCankaoJiaocheng/img/settings-s.png
JavascriptBiaozhunCankaoJiaocheng/img/settings.png
JavascriptBiaozhunCankaoJiaocheng/img/star.png
JavascriptBiaozhunCankaoJiaocheng/js/__init__.py
JavascriptBiaozhunCankaoJiaocheng/js/epub.js
JavascriptBiaozhunCankaoJiaocheng/js/epub.min.js
JavascriptBiaozhunCankaoJiaocheng/js/epub.min.map
JavascriptBiaozhunCankaoJiaocheng/js/hooks.min.js
JavascriptBiaozhunCankaoJiaocheng/js/hooks.min.map
JavascriptBiaozhunCankaoJiaocheng/js/reader.js
JavascriptBiaozhunCankaoJiaocheng/js/reader.js.map
JavascriptBiaozhunCankaoJiaocheng/js/reader.min.js
JavascriptBiaozhunCankaoJiaocheng/js/reader.min.map
javascript_biaozhun_cankao_jiaocheng-2024.3.1.0.dist-info/METADATA
javascript_biaozhun_cankao_jiaocheng-2024.3.1.0.dist-info/WHEEL
javascript_biaozhun_cankao_jiaocheng-2024.3.1.0.dist-info/entry_points.txt
javascript_biaozhun_cankao_jiaocheng-2024.3.1.0.dist-info/top_level.txt
javascript_biaozhun_cankao_jiaocheng-2024.3.1.0.dist-info/RECORD
